motor_apt/__init__.py
motor_apt/ell8.py
motor_apt/core/__init__.py
motor_apt/core/cr1.py
motor_apt/core/cr1_mockup.py
motor_apt/core/current_status.py
motor_apt/core/extended_controller.py
motor_apt/core/ftdi_device_mockup.py
motor_apt/core/main.py
motor_apt/core/message_listener.py
motor_apt/core/property_extensions.py
motor_apt/core/thorlabs_stage_device_mockup.py
motor_apt/core/timeout_exception.py
motor_apt/core/z612b.py
motor_apt/core/z812b.py
motor_apt/core/z812b_mockup.py
motor_apt/core/pyAPT/__init__.py
motor_apt/core/pyAPT/controller.py
motor_apt/core/pyAPT/message.py
motor_apt/core/pyAPT/mts50.py
motor_apt/core/pyAPT/prm1.py
motor_apt/core2/__init__.py
motor_apt/core2/controller.py
motor_apt/core2/cr1.py
motor_apt/core2/message.py
motor_apt/core2/message_device.py
motor_apt/tests/__init__.py
motor_apt/tests/test_cr1.py
motor_apt/tests/test_ui_motor_apt.py
motor_apt/tests/test_z812b.py
motor_apt/utils/__init__.py
motor_apt/utils/parser.py
motor_apt-2.0.8.dist-info/AUTHORS
motor_apt-2.0.8.dist-info/METADATA
motor_apt-2.0.8.dist-info/WHEEL
motor_apt-2.0.8.dist-info/entry_points.txt
motor_apt-2.0.8.dist-info/pbr.json
motor_apt-2.0.8.dist-info/top_level.txt
motor_apt-2.0.8.dist-info/RECORD
