Metadata-Version: 2.1
Name: motor-apt
Version: 2.0.8
Summary: Application for controlling motors from Thorlabs
Home-page: UNKNOWN
Author: juraj
License: BSD
Keywords: motor_apt
Platform: UNKNOWN
Classifier: Intended Audience :: Developers
Classifier: License :: OSI Approved :: BSD License
Classifier: Natural Language :: English
Classifier: Programming Language :: Python :: 2
Classifier: Programming Language :: Python :: 2.6
Classifier: Programming Language :: Python :: 2.7
License-File: AUTHORS
Requires-Dist: pylibftdi
Requires-Dist: enum34
